.bumpversion.cfg
.gitignore
.gitlab-ci.yml
HACKING.md
LICENSE
README.rst
requirements.txt
setup.cfg
setup.py
tox.ini
.githooks/pre-commit
.githooks/pre-push
.github/workflows/tox.yml
olx_utils.egg-info/PKG-INFO
olx_utils.egg-info/SOURCES.txt
olx_utils.egg-info/dependency_links.txt
olx_utils.egg-info/entry_points.txt
olx_utils.egg-info/requires.txt
olx_utils.egg-info/top_level.txt
olxutils/__init__.py
olxutils/__main__.py
olxutils/archive.py
olxutils/cli.py
olxutils/git.py
olxutils/helpers.py
olxutils/templates.py
olxutils/token.py
olxutils/upload.py
olxutils/templates/olx_partials.xml
requirements/base.txt
requirements/flake8.txt
requirements/setup.txt
requirements/test.txt
tests/__init__.py
tests/fenced-code-blocks.html
tests/fenced-code-blocks.md
tests/footnotes.html
tests/footnotes.md
tests/tasks.py
tests/test_cli.py
tests/test_full_course.py
tests/test_git.py
tests/test_helpers.py
tests/test_token.py
tests/test_upload.py
tests/course/result/README.md
tests/course/result/course.xml
tests/course/result/about/overview.html
tests/course/result/chapter/conclusion.xml
tests/course/result/chapter/introduction.xml
tests/course/result/html/README.md
tests/course/result/html/introduction_unit_01.html
tests/course/result/html/introduction_unit_02.html
tests/course/result/html/introduction_unit_03.html
tests/course/result/include/course.xml
tests/course/result/include/html/content.html
tests/course/result/include/html/lab.html
tests/course/result/include/sequential/content.xml
tests/course/result/include/sequential/lab.xml
tests/course/result/info/handouts.html
tests/course/result/info/updates.html
tests/course/result/markdown/README.md
tests/course/result/markdown/introduction_unit_01.md
tests/course/result/markdown/introduction_unit_02.md
tests/course/result/markdown/introduction_unit_03.md
tests/course/result/policies/assets.json
tests/course/result/policies/foo
tests/course/result/policies/_base/grading_policy.json
tests/course/result/policies/_base/policy.json
tests/course/result/sequential/README.md
tests/course/result/sequential/introduction.xml
tests/course/result/static/hot/README.md
tests/course/result/static/images/README.md
