Metadata-Version: 1.1
Name: olx-utils
Version: 0.3.4
Summary: Utilities for edX OLX courses
Home-page: https://github.com/hastexo/olx-utils
Author: hastexo
Author-email: pypi@hastexo.com
License: AGPL-3.0
Platform: UNKNOWN
Classifier: Development Status :: 3 - Alpha
Classifier: Intended Audience :: Education
Classifier: License :: OSI Approved :: GNU Affero General Public License v3
Classifier: Operating System :: POSIX :: Linux
Classifier: Programming Language :: Python :: 2.7
Classifier: Programming Language :: Python :: 3.5
Classifier: Programming Language :: Python :: 3.6
Classifier: Programming Language :: Python :: 3.7
Classifier: Programming Language :: Python :: 3.8
Classifier: Topic :: Education :: Computer Aided Instruction (CAI)
Classifier: Topic :: Education
